Metadata-Version: 2.1
Name: MLTestServier
Version: 0.1
Summary: solution
Home-page: UNKNOWN
License: UNKNOWN
Platform: UNKNOWN
